cligent/__init__.py
cligent/agents/__init__.py
cligent/agents/claude_code/__init__.py
cligent/agents/claude_code/core.py
cligent/agents/claude_code/utils.py
cligent/agents/codex_cli/__init__.py
cligent/agents/codex_cli/core.py
cligent/agents/gemini_cli/__init__.py
cligent/agents/gemini_cli/core.py
cligent/agents/qwen_code/__init__.py
cligent/agents/qwen_code/core.py
cligent/cli.py
cligent/cligent.py
cligent/core/__init__.py
cligent/core/errors.py
cligent/core/models.py
cligent-0.1.6.dist-info/METADATA
cligent-0.1.6.dist-info/WHEEL
cligent-0.1.6.dist-info/entry_points.txt
cligent-0.1.6.dist-info/RECORD
