Metadata-Version: 2.4
Name: cligent
Version: 0.1.6
Summary: Unified SDK for CLI agents (Claude Code, Gemini CLI, Qwen Coder)
Project-URL: Homepage, https://github.com/sublang-ai/cligent
Project-URL: Issues, https://github.com/sublang-ai/cligent/issues
Project-URL: Repository, https://github.com/sublang-ai/cligent.git
Author-email: Jinglei Ren <jinglei@merico.ai>
License: Apache-2.0
Keywords: agent,ai,claude,cli,gemini,orchestrator,qwen,task-execution
Classifier: Development Status :: 3 - Alpha
Classifier: Intended Audience :: Developers
Classifier: License :: OSI Approved :: Apache Software License
Classifier: Programming Language :: Python :: 3
Classifier: Programming Language :: Python :: 3.8
Classifier: Programming Language :: Python :: 3.9
Classifier: Programming Language :: Python :: 3.10
Classifier: Programming Language :: Python :: 3.11
Classifier: Programming Language :: Python :: 3.12
Classifier: Topic :: Software Development :: Libraries :: Python Modules
Requires-Python: >=3.8
Requires-Dist: pyyaml>=6.0
Provides-Extra: dev
Requires-Dist: mypy>=1.0.0; extra == 'dev'
Requires-Dist: pytest-cov>=4.0.0; extra == 'dev'
Requires-Dist: pytest>=7.0.0; extra == 'dev'
Requires-Dist: ruff>=0.1.0; extra == 'dev'
Requires-Dist: types-pyyaml>=6.0; extra == 'dev'
